.gitignore
LICENSE
MANIFEST.in
Pipfile
Pipfile.lock
README.md
setup.py
bin/inkscape-figures
community/YOUR_CODE_HERE.md
inkscape_figures_vscode.egg-info/PKG-INFO
inkscape_figures_vscode.egg-info/SOURCES.txt
inkscape_figures_vscode.egg-info/dependency_links.txt
inkscape_figures_vscode.egg-info/requires.txt
inkscape_figures_vscode.egg-info/top_level.txt
inkscapefigures/__init__.py
inkscapefigures/main.py
inkscapefigures/picker.py
inkscapefigures/template.svg