Metadata-Version: 2.1
Name: inkscape-figures-vscode
Version: 1.0.7
Summary: Script for managing inkscape figures (VsCode version created by gillescastel, modified by sleepymalc)
License: MIT
Platform: UNKNOWN
Classifier: License :: OSI Approved :: MIT License
Classifier: Programming Language :: Python :: 3
Classifier: Programming Language :: Python :: 3.7
License-File: LICENSE
